README.txt
setup.py
collective/__init__.py
collective.tabr.egg-info/PKG-INFO
collective.tabr.egg-info/SOURCES.txt
collective.tabr.egg-info/dependency_links.txt
collective.tabr.egg-info/entry_points.txt
collective.tabr.egg-info/namespace_packages.txt
collective.tabr.egg-info/not-zip-safe
collective.tabr.egg-info/requires.txt
collective.tabr.egg-info/top_level.txt
collective/tabr/__init__.py
collective/tabr/configure.zcml
collective/tabr/profiles.zcml
collective/tabr/setuphandlers.py
collective/tabr/skins.zcml
collective/tabr/tests.py
collective/tabr/browser/__init__.py
collective/tabr/browser/configure.zcml
collective/tabr/browser/tabr.js
collective/tabr/profiles/default/cssregistry.xml
collective/tabr/profiles/default/import_steps.xml
collective/tabr/profiles/default/jsregistry.xml
collective/tabr/profiles/default/metadata.xml
collective/tabr/profiles/default/skins.xml
collective/tabr/profiles/default/tabr_various.txt
collective/tabr/profiles/default/tinymce.xml
collective/tabr/skins/tabr/tabr_left_both.gif
collective/tabr/skins/tabr/tabr_right_both.gif
collective/tabr/skins/tabr/tabrtabs.css.dtml
collective/tabr/skins/tabr/tabrtabs.png
docs/HISTORY.txt
docs/INSTALL.txt
docs/LICENSE.GPL
docs/LICENSE.txt