Metadata-Version: 1.0
Name: collective.tabr
Version: 1.0
Summary: A simple package to add jQuery Tools Tabs UI support to Plone
Home-page: http://svn.plone.org/svn/collective/collective.tabr/
Author: Michael Dunlap
Author-email: dunlapm@uw.edu
License: GPL
Platform: UNKNOWN
Classifier: Framework :: Plone
Classifier: Programming Language :: Python
